fast_sentence_transformers/__init__.py
fast_sentence_transformers/fast_sentence_transformers.py
fast_sentence_transformers-0.5.dist-info/LICENSE
fast_sentence_transformers-0.5.dist-info/METADATA
fast_sentence_transformers-0.5.dist-info/WHEEL
fast_sentence_transformers-0.5.dist-info/RECORD
