Metadata-Version: 2.1
Name: fast-sentence-transformers
Version: 0.5
Summary: This repository contains code to run faster sentence-transformers. Simply, faster, sentence-transformers.
Home-page: https://github.com/pandora-intelligence/fast-sentence-transformers
License: MIT
Keywords: sentence-transformerx,ONNX,NLP
Author: David Berenstein
Author-email: david.m.berenstein@gmail.com
Requires-Python: >=3.9,<3.13
Classifier: Intended Audience :: Developers
Classifier: Intended Audience :: Science/Research
Classifier: License :: OSI Approved :: MIT License
Classifier: Operating System :: OS Independent
Classifier: Programming Language :: Python :: 3
Classifier: Programming Language :: Python :: 3.9
Classifier: Programming Language :: Python :: 3.10
Classifier: Programming Language :: Python :: 3.11
Classifier: Programming Language :: Python :: 3.12
Classifier: Programming Language :: Python :: 3.8
Classifier: Topic :: Scientific/Engineering
Classifier: Topic :: Software Development
Provides-Extra: gpu
Requires-Dist: numpy (<2)
Requires-Dist: optimum[onnxruntime] (>1.10,<2)
Requires-Dist: sentence-transformers (>=3,<4)
Requires-Dist: setuptools (>69)
Project-URL: Documentation, https://github.com/pandora-intelligence/fast-sentence-transformers
Project-URL: Repository, https://github.com/pandora-intelligence/fast-sentence-transformers
